odoo/addons/product_brand_stock/README.rst
odoo/addons/product_brand_stock/__init__.py
odoo/addons/product_brand_stock/__manifest__.py
odoo/addons/product_brand_stock/i18n/es.po
odoo/addons/product_brand_stock/i18n/it.po
odoo/addons/product_brand_stock/i18n/product_brand_stock.pot
odoo/addons/product_brand_stock/models/__init__.py
odoo/addons/product_brand_stock/models/stock_move.py
odoo/addons/product_brand_stock/models/stock_move_line.py
odoo/addons/product_brand_stock/models/stock_quant.py
odoo/addons/product_brand_stock/readme/CONTRIBUTORS.md
odoo/addons/product_brand_stock/readme/DESCRIPTION.md
odoo/addons/product_brand_stock/readme/USAGE.md
odoo/addons/product_brand_stock/static/description/icon.png
odoo/addons/product_brand_stock/static/description/index.html
odoo/addons/product_brand_stock/tests/__init__.py
odoo/addons/product_brand_stock/tests/test_product_brand_purchase.py
odoo/addons/product_brand_stock/views/stock_move_line_views.xml
odoo/addons/product_brand_stock/views/stock_move_views.xml
odoo/addons/product_brand_stock/views/stock_quant_views.xml
odoo_addon_product_brand_stock-18.0.1.0.0.2.dist-info/METADATA
odoo_addon_product_brand_stock-18.0.1.0.0.2.dist-info/WHEEL
odoo_addon_product_brand_stock-18.0.1.0.0.2.dist-info/top_level.txt
odoo_addon_product_brand_stock-18.0.1.0.0.2.dist-info/RECORD
